esam/__init__.py
esam/__main__.py
esam/esam.py
esam-1.1.2.dist-info/LICENSE
esam-1.1.2.dist-info/METADATA
esam-1.1.2.dist-info/WHEEL
esam-1.1.2.dist-info/entry_points.txt
esam-1.1.2.dist-info/top_level.txt
esam-1.1.2.dist-info/RECORD
