Metadata-Version: 2.1
Name: esam
Version: 1.1.2
Summary: eons sample analyzer and manager
Home-page: https://github.com/eons-dev/esam
Author: eons
Author-email: support@eons.dev
License: UNKNOWN
Project-URL: Bug Tracker, https://github.com/eons-dev/esam/issues
Platform: UNKNOWN
Classifier: Development Status :: 4 - Beta
Classifier: Programming Language :: Python :: 3
Classifier: License :: OSI Approved :: MIT License
Classifier: Operating System :: OS Independent
Requires-Python: >=3.6
License-File: LICENSE
Requires-Dist: jsonpickle
Requires-Dist: eons
